biomarker_mcp/__init__.py
biomarker_mcp/cli.py
biomarker_mcp/util.py
biomarker_mcp/data/Cell_marker_All.csv
biomarker_mcp/data/singleCellBase_20230904_ALL.txt
biomarker_mcp/schema/__int__.py
biomarker_mcp/schema/celltype.py
biomarker_mcp/server/__init__.py
biomarker_mcp/server/celltype.py
biomarker_mcp-0.2.1.dist-info/METADATA
biomarker_mcp-0.2.1.dist-info/WHEEL
biomarker_mcp-0.2.1.dist-info/entry_points.txt
biomarker_mcp-0.2.1.dist-info/RECORD
