Metadata-Version: 2.4
Name: biomarker-mcp
Version: 0.2.1
Summary: Natural language interface for celltype marker query through MCP.
Project-URL: Homepage, https://github.com/scmcphub/biomarker-mcp
Project-URL: Repository, https://github.com/scmcphub/biomarker-mcp
Author-email: shuang <hsh-me@outlook.com>
Keywords: AI,agent,bioinformatics,biomarker,celltype,gene marker,llm,mcp,model context protocol,scRNA-seq,single cell
Requires-Python: >=3.10
Requires-Dist: fastmcp>=2.3.4
Requires-Dist: mcp>=1.8.0
Requires-Dist: nest-asyncio
Requires-Dist: scanpy
Requires-Dist: typer
